wloc/__init__.py
wloc/exceptions.py
wloc/helpers.py
wloc/app/__init__.py
wloc/app/run.py
wloc/backends/__init__.py
wloc/backends/google.py
wloc/backends/mozilla.py
wloc/backends/yandex.py
wloc/fetchers/__init__.py
wloc/fetchers/factory.py
wloc/fetchers/native.py
wloc/fetchers/android/__init__.py
wloc/fetchers/android/termux.py
wloc/fetchers/linux/__init__.py
wloc/fetchers/linux/netman.py
wloc/fetchers/windows/__init__.py
wloc/fetchers/windows/structures.py
wloc/fetchers/windows/wlan.py
wloc-1.1.0.dist-info/LICENSE
wloc-1.1.0.dist-info/METADATA
wloc-1.1.0.dist-info/WHEEL
wloc-1.1.0.dist-info/entry_points.txt
wloc-1.1.0.dist-info/top_level.txt
wloc-1.1.0.dist-info/RECORD
