Metadata-Version: 2.1
Name: wloc
Version: 1.1.0
Summary: Simple Wi-Fi geolocation library and tool
Author-email: Vitaly Zaitsev <vitaly@easycoding.org>
License: GPL-3.0-or-later
Project-URL: homepage, https://github.com/xvitaly/wloc
Project-URL: documentation, https://github.com/xvitaly/wloc/blob/master/docs/README.md
Project-URL: repository, https://github.com/xvitaly/wloc
Keywords: api,application,geolocation,google-geolocation,library,mozilla-geolocation,tool,wi-fi,wi-fi-geolocation,yandex-geolocation
Classifier: Programming Language :: Python :: 3
Classifier: License :: OSI Approved :: GNU General Public License v3 (GPLv3)
Classifier: Operating System :: OS Independent
Requires-Python: >=3.6
License-File: LICENSE
Requires-Dist: requests (>=2.28.0)
Requires-Dist: pygobject (>=3.42.0) ; sys_platform == "linux"
Requires-Dist: comtypes (>=1.2.0) ; sys_platform == "win32"
Provides-Extra: deploy
Requires-Dist: pyinstaller (>=5.7.0) ; extra == 'deploy'
Provides-Extra: test
Requires-Dist: tox (>=3.27.0) ; extra == 'test'
